fastclash/__init__.py
fastclash/init.py
fastclash/main.py
fastclash/resources/install.sh
fastclash/resources/uninstall.sh
fastclash/resources/script/common.sh
fastclash/resources/script/download.sh
fastclash/resources/script/fastclash.sh
fastclash-1.3.1.dist-info/licenses/LICENSE
fastclash-1.3.1.dist-info/METADATA
fastclash-1.3.1.dist-info/WHEEL
fastclash-1.3.1.dist-info/entry_points.txt
fastclash-1.3.1.dist-info/top_level.txt
fastclash-1.3.1.dist-info/RECORD
