Metadata-Version: 2.4
Name: fastclash
Version: 1.3.1
Summary: Linux命令行使用Clash代理
Author-email: whillhill <ooooofish@126.com>
Maintainer-email: whillhill <ooooofish@126.com>
License-Expression: MIT
Project-URL: Homepage, https://github.com/whillhill/fastclash
Project-URL: Repository, https://github.com/whillhill/fastclash
Project-URL: Documentation, https://github.com/whillhill/fastclash/wiki
Project-URL: Bug Tracker, https://github.com/whillhill/fastclash/issues
Keywords: clash,proxy,vpn,linux,systemd,mihomo,installer
Classifier: Development Status :: 4 - Beta
Classifier: Intended Audience :: Developers
Classifier: Intended Audience :: System Administrators
Classifier: Operating System :: POSIX :: Linux
Classifier: Programming Language :: Python :: 3
Classifier: Programming Language :: Python :: 3.8
Classifier: Programming Language :: Python :: 3.9
Classifier: Programming Language :: Python :: 3.10
Classifier: Programming Language :: Python :: 3.11
Classifier: Programming Language :: Python :: 3.12
Classifier: Topic :: Internet :: Proxy Servers
Classifier: Topic :: System :: Networking
Classifier: Topic :: System :: Systems Administration
Classifier: Topic :: Software Development :: Libraries :: Python Modules
Requires-Python: >=3.8
License-File: LICENSE
Requires-Dist: click>=8.0.0
Provides-Extra: dev
Requires-Dist: pytest>=7.0; extra == "dev"
Requires-Dist: pytest-cov>=4.0; extra == "dev"
Requires-Dist: black>=22.0; extra == "dev"
Requires-Dist: flake8>=5.0; extra == "dev"
Requires-Dist: mypy>=1.0; extra == "dev"
Requires-Dist: pre-commit>=2.20; extra == "dev"
Requires-Dist: build>=0.10.0; extra == "dev"
Requires-Dist: twine>=4.0.0; extra == "dev"
Dynamic: license-file
